README.md
setup.py
ltp/__init__.py
ltp/__main__.py
ltp/const.py
ltp/fastltp.py
ltp/ltp.py
ltp/core/__init__.py
ltp/core/exceptions.py
ltp/core/registrable.py
ltp/data/__init__.py
ltp/data/dataloader.py
ltp/data/example.py
ltp/data/processing.py
ltp/data/utils.py
ltp/data/vocab.py
ltp/data/dataset/__init__.py
ltp/data/dataset/corpus.py
ltp/data/dataset/dataset.py
ltp/data/dataset/line.py
ltp/data/dataset/mixed.py
ltp/data/fields/__init__.py
ltp/data/fields/biaffine.py
ltp/data/fields/graph.py
ltp/data/fields/label.py
ltp/data/fields/sequence.py
ltp/data/fields/text.py
ltp/data/transforms/__init__.py
ltp/data/transforms/iobes.py
ltp/eval/__init__.py
ltp/eval/metrics/__init__.py
ltp/eval/metrics/accuracy.py
ltp/eval/metrics/biaffine_crf_span.py
ltp/eval/metrics/common_loss.py
ltp/eval/metrics/graph.py
ltp/eval/metrics/segment.py
ltp/eval/metrics/sequence.py
ltp/eval/metrics/tree.py
ltp/exe/__init__.py
ltp/exe/commands.py
ltp/exe/config.py
ltp/exe/executor.py
ltp/exe/task.py
ltp/models/__init__.py
ltp/models/model.py
ltp/models/multi_task_model.py
ltp/models/seq_tag_model.py
ltp/modules/__init__.py
ltp/modules/biaffine_crf.py
ltp/modules/bilinear_crf.py
ltp/modules/graph.py
ltp/modules/linear.py
ltp/modules/relative_transformer.py
ltp/nn/__init__.py
ltp/nn/activation.py
ltp/nn/biaffine.py
ltp/nn/bilinear.py
ltp/nn/crf.py
ltp/nn/ffnn.py
ltp/nn/mlp.py
ltp/nn/relative_transformer.py
ltp/nn/rnn.py
ltp/predict/__init__.py
ltp/predict/biaffine.py
ltp/predict/segment.py
ltp/predict/simple.py
ltp/train/__init__.py
ltp/train/checkpoint.py
ltp/train/callback/__init__.py
ltp/train/callback/csv_writer.py
ltp/train/callback/metric.py
ltp/train/callback/tensorboard.py
ltp/train/callback/validation.py
ltp/train/loss/__init__.py
ltp/train/loss/kd_loss.py
ltp/train/loss/task_loss.py
ltp/train/optim/__init__.py
ltp/train/optim/pretrained_optim.py
ltp/train/optim/task_optim.py
ltp/train/scheduler/__init__.py
ltp/train/scheduler/scheduler.py
ltp/train/scheduler/temperature_scheduler.py
ltp_kona.egg-info/PKG-INFO
ltp_kona.egg-info/SOURCES.txt
ltp_kona.egg-info/dependency_links.txt
ltp_kona.egg-info/requires.txt
ltp_kona.egg-info/top_level.txt