Metadata-Version: 2.1
Name: ltp-kona
Version: 4.0.9
Summary: Language Technology Platform
Home-page: https://github.com/HIT-SCIR/ltp
Author: Yunlong Feng
Author-email: ylfeng@ir.hit.edu.cn
License: UNKNOWN
Platform: UNKNOWN
Classifier: Development Status :: 1 - Planning
Classifier: Operating System :: OS Independent
Classifier: Intended Audience :: Developers
Classifier: Programming Language :: Python :: 3.6
Classifier: Programming Language :: Python :: 3.7
Classifier: Programming Language :: Python :: 3.8
Classifier: Topic :: Software Development :: Libraries
Requires-Python: >=3.6.*, <4
